CytoOne/__init__.py
CytoOne/__main__.py
CytoOne/__version__.py
CytoOne/basic_distributions.py
CytoOne/cytoone_class.py
CytoOne/decoder.py
CytoOne/encoder.py
CytoOne/utilities.py
cytoone-0.0.2.dist-info/licenses/LICENSE
cytoone-0.0.2.dist-info/METADATA
cytoone-0.0.2.dist-info/WHEEL
cytoone-0.0.2.dist-info/top_level.txt
cytoone-0.0.2.dist-info/RECORD
