Metadata-Version: 2.4
Name: CytoOne
Version: 0.0.2
Summary: A unified probabilistic framework for CyTOF data
Author: Yuqiu Yang; Kaiwen Wang; Xinlei Wang
Author-email: yuqiu.yang@utsouthwestern.edu; @.edu; @.edu
Classifier: Programming Language :: Python :: 3 :: Only
Classifier: Natural Language :: English
Classifier: Intended Audience :: Science/Research
Requires-Python: >=3.9,<3.11
License-File: LICENSE
Requires-Dist: numpy<2.0
Requires-Dist: pandas>=2.2.0
Requires-Dist: anndata<0.11,>=0.10
Requires-Dist: scanpy<1.11
Requires-Dist: torch<2.0
Requires-Dist: pyro-ppl<1.8.5
Requires-Dist: seaborn
Requires-Dist: jupyter
Requires-Dist: ipywidgets
Dynamic: author
Dynamic: author-email
Dynamic: classifier
Dynamic: description
Dynamic: description-content-type
Dynamic: license-file
Dynamic: requires-dist
Dynamic: requires-python
Dynamic: summary
